apiref
