Metadata-Version: 1.1
Name: apiref
Version: 0.2.0
Summary: library
Home-page: https://github.com/novopl/apiref
Author: Mateusz Klos
Author-email: novopl@gmail.com
License: Apache 2.0
Keywords: library
Platform: UNKNOWN
Classifier: Development Status :: 3 - Alpha
Classifier: Intended Audience :: Developers
Classifier: Typing :: Typed
Classifier: Programming Language :: Python
Classifier: Programming Language :: Python :: 3
Classifier: License :: OSI Approved :: Apache Software License
